remoterl-1.1.5.dist-info/RECORD
remoterl-1.1.5.dist-info/WHEEL
remoterl-1.1.5.dist-info/entry_points.txt
remoterl-1.1.5.dist-info/top_level.txt
remoterl-1.1.5.dist-info/METADATA
remoterl-1.1.5.dist-info/licenses/LICENSE.txt
remoterl/_remote_exception.py
remoterl/config.py
remoterl/__init__.py
remoterl/_rllib_wrapper.py
remoterl/_internal/_mod3.cpython-39-darwin.so
remoterl/_internal/_mod24.cpython-39-darwin.so
remoterl/_internal/_mod21.cpython-39-darwin.so
remoterl/_internal/_mod19.cpython-39-darwin.so
remoterl/_internal/_mod2.cpython-39-darwin.so
remoterl/_internal/_mod25.cpython-39-darwin.so
remoterl/_internal/__init__.py
remoterl/_internal/_mod20.cpython-39-darwin.so
remoterl/_internal/_mod23.cpython-39-darwin.so
remoterl/_internal/_mod1.cpython-39-darwin.so
remoterl/_internal/_mod4.cpython-39-darwin.so
remoterl/_internal/_mod22.cpython-39-darwin.so
remoterl/_internal/learner/_mod9.cpython-39-darwin.so
remoterl/_internal/learner/__init__.py
remoterl/_internal/learner/_mod18.cpython-39-darwin.so
remoterl/_internal/learner/_mod17.cpython-39-darwin.so
remoterl/_internal/learner/_mod10.cpython-39-darwin.so
remoterl/_internal/learner/_mod0.cpython-39-darwin.so
remoterl/_internal/learner/proc/_mod13.cpython-39-darwin.so
remoterl/_internal/learner/proc/__init__.py
remoterl/_internal/learner/proc/_mod12.cpython-39-darwin.so
remoterl/_internal/learner/proc/_mod11.cpython-39-darwin.so
remoterl/_internal/learner/thread/_mod16.cpython-39-darwin.so
remoterl/_internal/learner/thread/__init__.py
remoterl/_internal/learner/thread/_mod14.cpython-39-darwin.so
remoterl/_internal/learner/thread/_mod15.cpython-39-darwin.so
remoterl/_internal/environment/_mod6.cpython-39-darwin.so
remoterl/_internal/environment/_mod7.cpython-39-darwin.so
remoterl/_internal/environment/_mod8.cpython-39-darwin.so
remoterl/_internal/environment/__init__.py
remoterl/_internal/environment/_mod5.cpython-39-darwin.so
remoterl/pipelines/gym.py
remoterl/pipelines/rllib.py
remoterl/pipelines/simulate.py
remoterl/pipelines/sb3.py
remoterl/pipelines/__init__.py
remoterl/pipelines/train.py
remoterl/pipelines/helpers.py
remoterl/cli/__init__.py
remoterl/cli/__main__.py
