Metadata-Version: 2.4
Name: remoterl
Version: 1.1.5
Summary: RemoteRL: high-performance command-line & Python client with pre-compiled native wheels for remote reinforcement-learning workloads.
Home-page: https://remoterl.com
Author: JunHo Park
Author-email: support@ccnets.org
License: REMOTE RL COMMERCIAL LICENSE
Project-URL: Source, https://github.com/ccnets-team/remoterl
Project-URL: Bug Tracker, https://github.com/ccnets-team/remoterl/issues
Keywords: remote rl reinforcement-learning online-learning gymnasium ray rllib stable-baselines3
Classifier: Programming Language :: Python :: 3
Classifier: License :: Other/Proprietary License
Classifier: Operating System :: OS Independent
Requires-Python: >=3.9
License-File: LICENSE.txt
Requires-Dist: gymnasium
Requires-Dist: msgpack
Requires-Dist: websockets
Requires-Dist: lz4
Requires-Dist: typer
Requires-Dist: virtualenv
Provides-Extra: rllib
Requires-Dist: ray[rllib]; extra == "rllib"
Requires-Dist: pillow; extra == "rllib"
Provides-Extra: stable-baselines3
Requires-Dist: stable-baselines3; extra == "stable-baselines3"
Dynamic: author
Dynamic: author-email
Dynamic: classifier
Dynamic: description
Dynamic: description-content-type
Dynamic: home-page
Dynamic: keywords
Dynamic: license
Dynamic: license-file
Dynamic: project-url
Dynamic: provides-extra
Dynamic: requires-dist
Dynamic: requires-python
Dynamic: summary
